[
  {
    "firstName": "Alberto",
    "lastName": "Falberto",
    "id": 1648037975497,
    "userName": "Gilberte",
    "password": "1",
    "pro": false,
    "size": 20,
    "volume": 0,
    "voice": ""
  },
  {
    "firstName": "Albert",
    "lastName": "Falbert",
    "id": 1648037975498,
    "userName": "AF",
    "password": "1",
    "pro": false,
    "size": 20,
    "volume": 1,
    "voice": ""
  },
  {
    "firstName": "Pierre",
    "lastName": "Pierre",
    "id": 1648037975499,
    "userName": "Pierre",
    "password": "pierre",
    "pro": true
  }
]
